flyteidl/__init__.py
flyteidl/admin/__init__.py
flyteidl/admin/agent_pb2.py
flyteidl/admin/agent_pb2.pyi
flyteidl/admin/agent_pb2_grpc.py
flyteidl/admin/cluster_assignment_pb2.py
flyteidl/admin/cluster_assignment_pb2.pyi
flyteidl/admin/cluster_assignment_pb2_grpc.py
flyteidl/admin/common_pb2.py
flyteidl/admin/common_pb2.pyi
flyteidl/admin/common_pb2_grpc.py
flyteidl/admin/description_entity_pb2.py
flyteidl/admin/description_entity_pb2.pyi
flyteidl/admin/description_entity_pb2_grpc.py
flyteidl/admin/event_pb2.py
flyteidl/admin/event_pb2.pyi
flyteidl/admin/event_pb2_grpc.py
flyteidl/admin/execution_pb2.py
flyteidl/admin/execution_pb2.pyi
flyteidl/admin/execution_pb2_grpc.py
flyteidl/admin/launch_plan_pb2.py
flyteidl/admin/launch_plan_pb2.pyi
flyteidl/admin/launch_plan_pb2_grpc.py
flyteidl/admin/matchable_resource_pb2.py
flyteidl/admin/matchable_resource_pb2.pyi
flyteidl/admin/matchable_resource_pb2_grpc.py
flyteidl/admin/node_execution_pb2.py
flyteidl/admin/node_execution_pb2.pyi
flyteidl/admin/node_execution_pb2_grpc.py
flyteidl/admin/notification_pb2.py
flyteidl/admin/notification_pb2.pyi
flyteidl/admin/notification_pb2_grpc.py
flyteidl/admin/project_attributes_pb2.py
flyteidl/admin/project_attributes_pb2.pyi
flyteidl/admin/project_attributes_pb2_grpc.py
flyteidl/admin/project_domain_attributes_pb2.py
flyteidl/admin/project_domain_attributes_pb2.pyi
flyteidl/admin/project_domain_attributes_pb2_grpc.py
flyteidl/admin/project_pb2.py
flyteidl/admin/project_pb2.pyi
flyteidl/admin/project_pb2_grpc.py
flyteidl/admin/schedule_pb2.py
flyteidl/admin/schedule_pb2.pyi
flyteidl/admin/schedule_pb2_grpc.py
flyteidl/admin/signal_pb2.py
flyteidl/admin/signal_pb2.pyi
flyteidl/admin/signal_pb2_grpc.py
flyteidl/admin/task_execution_pb2.py
flyteidl/admin/task_execution_pb2.pyi
flyteidl/admin/task_execution_pb2_grpc.py
flyteidl/admin/task_pb2.py
flyteidl/admin/task_pb2.pyi
flyteidl/admin/task_pb2_grpc.py
flyteidl/admin/version_pb2.py
flyteidl/admin/version_pb2.pyi
flyteidl-1.16.1.dist-info/licenses/LICENSE
flyteidl-1.16.1.dist-info/licenses/NOTICE
flyteidl-1.16.1.dist-info/METADATA
flyteidl-1.16.1.dist-info/WHEEL
flyteidl-1.16.1.dist-info/top_level.txt
flyteidl-1.16.1.dist-info/RECORD
