Metadata-Version: 2.4
Name: flyteidl
Version: 1.16.1
Summary: IDL for Flyte Platform
Author-email: Flyte Contributors <admin@flyte.org>
License: Apache-2.0
Project-URL: Homepage, https://github.com/flyteorg/flyte/tree/master/flyteidl
Classifier: Intended Audience :: Science/Research
Classifier: Intended Audience :: Developers
Classifier: License :: OSI Approved :: Apache Software License
Classifier: Programming Language :: Python :: 3.8
Classifier: Programming Language :: Python :: 3.9
Classifier: Programming Language :: Python :: 3.10
Classifier: Programming Language :: Python :: 3.11
Classifier: Programming Language :: Python :: 3.12
Classifier: Topic :: Scientific/Engineering
Classifier: Topic :: Scientific/Engineering :: Artificial Intelligence
Classifier: Topic :: Software Development
Classifier: Topic :: Software Development :: Libraries
Classifier: Topic :: Software Development :: Libraries :: Python Modules
Requires-Python: <3.13,>=3.8
License-File: LICENSE
License-File: NOTICE
Requires-Dist: googleapis-common-protos
Requires-Dist: protoc-gen-openapiv2
Requires-Dist: protobuf>=4.21.1
Dynamic: license-file
